{
  "updated_at": "2026-04-26 18:40",
  "items": [
    {
      "title": "Assessing CellaVision (OM:CEVI) Valuation After Recent Boardroom Changes",
      "link": "https://finance.yahoo.com/markets/stocks/articles/assessing-cellavision-om-cevi-valuation-100719090.html",
      "publisher": "Simply Wall St.",
      "time": "2026-04-26T10:07:19.000Z"
    },
    {
      "title": "HELOC and home equity loan rates Sunday, April 26, 2026: Rates mostly unchanged",
      "link": "https://finance.yahoo.com/personal-finance/mortgages/article/heloc-home-equity-loan-interest-rates-today-sunday-april-26-2026-100000982.html",
      "publisher": "Yahoo Personal Finance",
      "time": "2026-04-26T10:00:00.000Z"
    },
    {
      "title": "Is Ameriprise Financial (AMP) Still Attractive After Doubling Over The Past Five Years",
      "link": "https://finance.yahoo.com/markets/stocks/articles/ameriprise-financial-amp-still-attractive-100327982.html",
      "publisher": "Simply Wall St.",
      "time": "2026-04-26T10:03:27.000Z"
    },
    {
      "title": "Has The Recent Rally Left Dell Technologies (DELL) Fully Priced Or Still Attractive?",
      "link": "https://finance.yahoo.com/markets/stocks/articles/recent-rally-left-dell-technologies-100351256.html",
      "publisher": "Simply Wall St.",
      "time": "2026-04-26T10:03:51.000Z"
    }
  ]
}