{
  "updated_at": "2026-04-17 06:20",
  "items": [
    {
      "title": "France finance minister says Hormuz must open, G7 ready to mitigate war fallout",
      "link": "https://finance.yahoo.com/m/69a12fef-f685-3893-a4eb-9f375f9a3779/france-finance-minister-says.html",
      "publisher": "AFP",
      "time": "2026-04-16T20:41:28.000Z"
    },
    {
      "title": "S&P 500 rallies to new record, Spirit Airlines at risk of bankruptcy",
      "link": "https://finance.yahoo.com/video/sp-500-rallies-to-new-record-spirit-airlines-at-risk-of-bankruptcy-181237588.html",
      "publisher": "Yahoo Finance Video",
      "time": "2026-04-16T18:12:37.000Z"
    },
    {
      "title": "Chicago Atlantic Real Estate Finance Schedules First Quarter 2026 Earnings Release and Conference Call Date",
      "link": "https://finance.yahoo.com/markets/stocks/articles/chicago-atlantic-real-estate-finance-201500598.html",
      "publisher": "GlobeNewswire",
      "time": "2026-04-16T20:15:00.000Z"
    },
    {
      "title": "What the S&P 500 might be telling us",
      "link": "https://finance.yahoo.com/video/what-the-sp-500-might-be-telling-us-195358665.html",
      "publisher": "Yahoo Finance Video",
      "time": "2026-04-16T19:53:58.000Z"
    }
  ]
}