{
  "updated_at": "2026-04-30 20:20",
  "items": [
    {
      "title": "NREF Announces First Quarter 2026 Results, Provides Second Quarter 2026 Guidance",
      "link": "https://finance.yahoo.com/markets/stocks/articles/nref-announces-first-quarter-2026-121500235.html",
      "publisher": "PR Newswire",
      "time": "2026-04-30T12:15:00.000Z"
    },
    {
      "title": "DISA Technologies Closes $33M Strategic Financing Led by Galvanize and Supported by BHP Ventures",
      "link": "https://finance.yahoo.com/sectors/energy/articles/disa-technologies-closes-33m-strategic-120000776.html",
      "publisher": "PR Newswire",
      "time": "2026-04-30T12:00:00.000Z"
    },
    {
      "title": "Five-Star Business Finance Ltd (BOM:543663) Q4 2026 Earnings Call Highlights: Strong Collection ...",
      "link": "https://finance.yahoo.com/markets/stocks/articles/five-star-business-finance-ltd-070051208.html",
      "publisher": "GuruFocus.com",
      "time": "2026-04-30T07:00:51.000Z"
    },
    {
      "title": "Apollo Commercial Real Estate Finance Q1 Earnings Call Highlights",
      "link": "https://finance.yahoo.com/m/42f7eb50-bad9-3c67-b76a-0e779d1c4141/apollo-commercial-real-estate.html",
      "publisher": "MarketBeat",
      "time": "2026-04-30T02:42:00.000Z"
    }
  ]
}