{
  "updated_at": "2026-04-26 20:50",
  "items": [
    {
      "title": "Consumers are confusing the hell out of me. What am I missing?",
      "link": "https://finance.yahoo.com/news/consumers-are-confusing-the-hell-out-of-me-what-am-i-missing-123053559.html",
      "publisher": "Yahoo Finance",
      "time": "2026-04-26T12:30:53.000Z"
    },
    {
      "title": "Mag 7 earnings bonanza and Powell's home stretch: What to watch this week",
      "link": "https://finance.yahoo.com/news/mag-7-earnings-bonanza-and-powells-home-stretch-what-to-watch-this-week-113016596.html",
      "publisher": "Yahoo Finance",
      "time": "2026-04-26T11:30:16.000Z"
    },
    {
      "title": "Assessing KKR (KKR) Valuation After A Short-Term Rebound And Conflicting Earnings Signals",
      "link": "https://finance.yahoo.com/markets/stocks/articles/assessing-kkr-kkr-valuation-short-120453557.html",
      "publisher": "Simply Wall St.",
      "time": "2026-04-26T12:04:53.000Z"
    },
    {
      "title": "Assessing Whether Nova (NVMI) Still Looks Overvalued After Its Strong Recent Share Price Run",
      "link": "https://finance.yahoo.com/markets/stocks/articles/assessing-whether-nova-nvmi-still-120342309.html",
      "publisher": "Simply Wall St.",
      "time": "2026-04-26T12:03:42.000Z"
    }
  ]
}