{
  "updated_at": "2026-05-24 16:10",
  "items": [
    {
      "title": "Assessing BILL Holdings (BILL) Valuation After Earnings Beat AI Push And US$1b Buyback Authorization",
      "link": "https://finance.yahoo.com/markets/stocks/articles/assessing-bill-holdings-bill-valuation-070954309.html",
      "publisher": "Simply Wall St.",
      "time": "2026-05-24T07:09:54.000Z"
    },
    {
      "title": "A Look At American States Water (AWR) Valuation After Recent Mixed Share Performance",
      "link": "https://finance.yahoo.com/markets/stocks/articles/look-american-states-water-awr-071129692.html",
      "publisher": "Simply Wall St.",
      "time": "2026-05-24T07:11:29.000Z"
    },
    {
      "title": "Vinci Pitch Book Sets Long Term Infrastructure And Sustainability Context",
      "link": "https://finance.yahoo.com/markets/stocks/articles/vinci-pitch-book-sets-long-071027725.html",
      "publisher": "Simply Wall St.",
      "time": "2026-05-24T07:10:27.000Z"
    },
    {
      "title": "Is It Too Late To Reassess Delivery Hero (XTRA:DHER) After The Recent 72.3% Monthly Surge",
      "link": "https://finance.yahoo.com/markets/stocks/articles/too-reassess-delivery-hero-xtra-070935804.html",
      "publisher": "Simply Wall St.",
      "time": "2026-05-24T07:09:35.000Z"
    }
  ]
}