{
  "updated_at": "2026-04-20 03:20",
  "items": [
    {
      "title": "Graham Stephan Says 'Nothing Makes Sense Anymore' As S&P 500 And Nasdaq Break Records. Here's His Strategy For Retirement",
      "link": "https://finance.yahoo.com/markets/stocks/articles/graham-stephan-says-nothing-makes-163126617.html",
      "publisher": "Benzinga",
      "time": "2026-04-19T16:31:26.000Z"
    },
    {
      "title": "Intuit’s FedNow Move Links Real Time Payments With Undervalued Shares",
      "link": "https://finance.yahoo.com/markets/stocks/articles/intuit-fednow-move-links-real-140305649.html",
      "publisher": "Simply Wall St.",
      "time": "2026-04-19T14:03:05.000Z"
    },
    {
      "title": "Assessing TRX Gold’s Valuation After Buckreef Production Gains And Plant Expansion Progress",
      "link": "https://finance.yahoo.com/news/assessing-trx-gold-valuation-buckreef-180343404.html",
      "publisher": "Simply Wall St.",
      "time": "2026-04-19T18:03:43.000Z"
    },
    {
      "title": "A Look At Clover Health Investments (CLOV) Valuation As Shares Rebound Over The Past Week",
      "link": "https://finance.yahoo.com/markets/stocks/articles/look-clover-health-investments-clov-180317403.html",
      "publisher": "Simply Wall St.",
      "time": "2026-04-19T18:03:17.000Z"
    }
  ]
}