{
  "updated_at": "2026-04-12 04:00",
  "items": [
    {
      "title": "Entergy Finance Shift Puts Focus On Dividend And Reporting Consistency",
      "link": "https://finance.yahoo.com/markets/stocks/articles/entergy-finance-shift-puts-focus-181014922.html",
      "publisher": "Simply Wall St.",
      "time": "2026-04-11T18:10:14.000Z"
    },
    {
      "title": "Assessing Chiyoda (TSE:6366) Valuation After Strong Multi‑Month Share Price Momentum",
      "link": "https://finance.yahoo.com/markets/stocks/articles/assessing-chiyoda-tse-6366-valuation-191356808.html",
      "publisher": "Simply Wall St.",
      "time": "2026-04-11T19:13:56.000Z"
    },
    {
      "title": "Assessing NOW Corporation (PSE:NOW) Valuation As High P/S Meets Mixed Recent Returns",
      "link": "https://finance.yahoo.com/markets/stocks/articles/assessing-now-corporation-pse-now-191300872.html",
      "publisher": "Simply Wall St.",
      "time": "2026-04-11T19:13:00.000Z"
    },
    {
      "title": "Is It Too Late To Consider TJX Companies (TJX) After A 28% One Year Gain?",
      "link": "https://finance.yahoo.com/markets/stocks/articles/too-consider-tjx-companies-tjx-191211017.html",
      "publisher": "Simply Wall St.",
      "time": "2026-04-11T19:12:11.000Z"
    }
  ]
}