{
  "updated_at": "2026-05-15 10:40",
  "items": [
    {
      "title": "Power Finance Corp Ltd (BOM:532810) Q4 2026 Earnings Call Highlights: Record Profits and ...",
      "link": "https://finance.yahoo.com/markets/stocks/articles/power-finance-corp-ltd-bom-010253650.html",
      "publisher": "GuruFocus.com",
      "time": "2026-05-15T01:02:53.000Z"
    },
    {
      "title": "Muthoot Finance Ltd (BOM:533398) Q4 2026 Earnings Call Highlights: Record Growth and Strategic ...",
      "link": "https://finance.yahoo.com/markets/stocks/articles/muthoot-finance-ltd-bom-533398-230353356.html",
      "publisher": "GuruFocus.com",
      "time": "2026-05-14T23:03:53.000Z"
    },
    {
      "title": "TPG RE Finance Trust Closes $400 Million Term Loan B, $100 Million Revolving Credit Facility",
      "link": "https://finance.yahoo.com/markets/stocks/articles/tpg-finance-trust-closes-400-212110238.html",
      "publisher": "MT Newswires",
      "time": "2026-05-14T21:21:10.000Z"
    },
    {
      "title": "Banorte, led by Carlos Hank González, is recognized as the \"Best Foreign Trade Finance Provider\" by Global Finance",
      "link": "https://finance.yahoo.com/economy/policy/articles/banorte-led-carlos-hank-gonz-231000080.html",
      "publisher": "PR Newswire",
      "time": "2026-05-14T23:10:00.000Z"
    }
  ]
}