{
  "updated_at": "2026-05-10 20:40",
  "items": [
    {
      "title": "Genpact Google Cloud Alliance Puts AI Finance Push And Valuation In Focus",
      "link": "https://finance.yahoo.com/markets/stocks/articles/genpact-google-cloud-alliance-puts-101021558.html",
      "publisher": "Simply Wall St.",
      "time": "2026-05-10T10:10:21.000Z"
    },
    {
      "title": "Assessing United Airlines (UAL) Valuation As Recent Share Price Moves Leave Sentiment Split",
      "link": "https://finance.yahoo.com/markets/stocks/articles/assessing-united-airlines-ual-valuation-120723523.html",
      "publisher": "Simply Wall St.",
      "time": "2026-05-10T12:07:23.000Z"
    },
    {
      "title": "Is Essential Utilities (WTRG) Offering Value After Recent Share Price Weakness",
      "link": "https://finance.yahoo.com/markets/stocks/articles/essential-utilities-wtrg-offering-value-120750084.html",
      "publisher": "Simply Wall St.",
      "time": "2026-05-10T12:07:50.000Z"
    },
    {
      "title": "Is It Too Late To Consider STMicroelectronics (ENXTPA:STMPA) After Its Surging Share Price?",
      "link": "https://finance.yahoo.com/markets/stocks/articles/too-consider-stmicroelectronics-enxtpa-stmpa-120556220.html",
      "publisher": "Simply Wall St.",
      "time": "2026-05-10T12:05:56.000Z"
    }
  ]
}