{
  "updated_at": "2026-05-19 05:10",
  "items": [
    {
      "title": "G7 finance chiefs meet to seek common stance on unstable ground",
      "link": "https://finance.yahoo.com/economy/policy/articles/g7-finance-chiefs-meet-seek-063158764.html",
      "publisher": "AFP",
      "time": "2026-05-18T09:33:23.000Z"
    },
    {
      "title": "Africa Finance Corporation Approves US$100 Million Commitment to Africa-Focused Technology Fund Managers to Accelerate Africa’s Digital Industrialisation",
      "link": "https://finance.yahoo.com/sectors/technology/articles/africa-finance-corporation-approves-us-185000026.html",
      "publisher": "ACCESS Newswire",
      "time": "2026-05-18T18:50:00.000Z"
    },
    {
      "title": "OneStream Unveils Forward Finance Blueprint to Help CFOs Lead Enterprise AI and Future-Proof the Business",
      "link": "https://finance.yahoo.com/sectors/technology/articles/onestream-unveils-forward-finance-blueprint-130000919.html",
      "publisher": "PR Newswire",
      "time": "2026-05-18T13:00:00.000Z"
    },
    {
      "title": "Bond market is losing 'a bit of faith' in Fed's inflation handling",
      "link": "https://finance.yahoo.com/video/bond-market-is-losing-a-bit-of-faith-in-feds-inflation-handling-194646361.html",
      "publisher": "Yahoo Finance Video",
      "time": "2026-05-18T19:46:46.000Z"
    }
  ]
}