{
  "updated_at": "2026-04-13 20:10",
  "items": [
    {
      "title": "Julius Baer finance chief to step down",
      "link": "https://finance.yahoo.com/m/69aa8e83-751d-3baf-82eb-b795eee2b991/julius-baer-finance-chief.html",
      "publisher": "Private Banker International",
      "time": "2026-04-13T11:46:56.000Z"
    },
    {
      "title": "Deepfake Wire Fraud is Surging: LegalMatch Advises Businesses on Navigating Complex Wire Recovery Protocols",
      "link": "https://finance.yahoo.com/sectors/technology/articles/deepfake-wire-fraud-surging-legalmatch-110000015.html",
      "publisher": "ACCESS Newswire",
      "time": "2026-04-13T11:00:00.000Z"
    },
    {
      "title": "Finance minister favourite as Benin votes for president",
      "link": "https://finance.yahoo.com/m/c847ffc6-df11-3b06-9dba-26eefd809700/finance-minister-favourite-as.html",
      "publisher": "AFP",
      "time": "2026-04-12T17:19:15.000Z"
    },
    {
      "title": "Envision Energy, BBVA sign $500m vendor financing agreement",
      "link": "https://finance.yahoo.com/m/59f262e6-df99-3f43-824f-5a40c1408ea3/envision-energy%2C-bbva-sign.html",
      "publisher": "Power Technology",
      "time": "2026-04-13T08:32:42.000Z"
    }
  ]
}