{
  "updated_at": "2026-05-25 22:20",
  "items": [
    {
      "title": "Used Car Financing Market Strategies and Forecasts Report 2026-2034 - Rising Penetration of Digital Loan Origination, and Continued Shift of Value-conscious Buyers Toward Used Vehicles",
      "link": "https://finance.yahoo.com/markets/stocks/articles/used-car-financing-market-strategies-101700633.html",
      "publisher": "GlobeNewswire",
      "time": "2026-05-25T10:17:00.000Z"
    },
    {
      "title": "Is Bread Financial Holdings (BFH) Still Attractive After A 73% One Year Share Price Jump",
      "link": "https://finance.yahoo.com/markets/stocks/articles/bread-financial-holdings-bfh-still-111001684.html",
      "publisher": "Simply Wall St.",
      "time": "2026-05-25T11:10:01.000Z"
    },
    {
      "title": "Due to Overwhelming Demand Coyote Copper Mines Inc. Announces Upsizing the Non-Brokered Financing to $7 Million",
      "link": "https://finance.yahoo.com/markets/stocks/articles/due-overwhelming-demand-coyote-copper-110000773.html",
      "publisher": "TMX Newsfile",
      "time": "2026-05-25T11:00:00.000Z"
    },
    {
      "title": "A Look At GATX (GATX) Valuation After Recent Share Price Pressure",
      "link": "https://finance.yahoo.com/markets/stocks/articles/look-gatx-gatx-valuation-recent-131406665.html",
      "publisher": "Simply Wall St.",
      "time": "2026-05-25T13:14:06.000Z"
    }
  ]
}