{
  "updated_at": "2026-04-12 21:30",
  "items": [
    {
      "title": "Finance minister favourite as Benin votes for president",
      "link": "https://finance.yahoo.com/m/c847ffc6-df11-3b06-9dba-26eefd809700/finance-minister-favourite-as.html",
      "publisher": "AFP",
      "time": "2026-04-12T11:50:49.000Z"
    },
    {
      "title": "Best Nonprofit Budgeting Software for Finance Teams and Grant Management",
      "link": "https://finance.yahoo.com/sectors/technology/articles/best-nonprofit-budgeting-software-finance-213200267.html",
      "publisher": "GlobeNewswire",
      "time": "2026-04-11T21:32:00.000Z"
    },
    {
      "title": "I hate to be the bad guy on the stock market",
      "link": "https://finance.yahoo.com/news/i-hate-to-be-the-bad-guy-on-the-stock-market-123027225.html",
      "publisher": "Yahoo Finance",
      "time": "2026-04-12T12:30:27.000Z"
    },
    {
      "title": "Erie Indemnity Has Spent a Century Collecting a Fee. The Market Still Prices It Like an Insurer.",
      "link": "https://finance.yahoo.com/markets/stocks/articles/erie-indemnity-spent-century-collecting-125204382.html",
      "publisher": "GuruFocus.com",
      "time": "2026-04-12T12:52:04.000Z"
    }
  ]
}