{
  "updated_at": "2026-04-01 17:30",
  "items": [
    {
      "title": "A Look At Alkane Resources (ASX:ALK) Valuation After Its New A$150 Million Debt Facilities",
      "link": "https://finance.yahoo.com/markets/stocks/articles/look-alkane-resources-asx-alk-071556449.html",
      "publisher": "Simply Wall St.",
      "time": "2026-04-01T07:15:56.000Z"
    },
    {
      "title": "Should Trade Desk’s (TTD) Board Shuffle Subtly Reframe Its Governance Story for Long-Term Investors?",
      "link": "https://finance.yahoo.com/markets/stocks/articles/trade-desk-ttd-board-shuffle-081728387.html",
      "publisher": "Simply Wall St.",
      "time": "2026-04-01T08:17:28.000Z"
    },
    {
      "title": "Lake Victoria Gold Secures up to a ~US$25 Million Gold Loan from Monetary Metals plus Fully Committed $3.0 Million Convertible Debenture Financing",
      "link": "https://finance.yahoo.com/markets/commodities/articles/lake-victoria-gold-secures-us-070100271.html",
      "publisher": "TMX Newsfile",
      "time": "2026-04-01T07:01:00.000Z"
    },
    {
      "title": "Consumer spending has powered US economic growth. The Iran war is 'testing its resilience.'",
      "link": "https://finance.yahoo.com/news/consumer-spending-has-powered-us-economic-growth-the-iran-war-is-testing-its-resilience-090043647.html",
      "publisher": "Yahoo Finance",
      "time": "2026-04-01T09:00:43.000Z"
    }
  ]
}