{
  "updated_at": "2026-05-03 21:50",
  "items": [
    {
      "title": "10 things to consider before relocating in retirement",
      "link": "https://finance.yahoo.com/video/10-things-consider-relocating-retirement-120000221.html",
      "publisher": "Yahoo Finance Video",
      "time": "2026-05-03T12:00:00.000Z"
    },
    {
      "title": "'It's a boom': Wall Street sees more market gains as strong earnings fuel the AI trade",
      "link": "https://finance.yahoo.com/markets/article/its-a-boom-wall-street-sees-more-market-gains-as-strong-earnings-fuel-the-ai-trade-130032453.html",
      "publisher": "Yahoo Finance",
      "time": "2026-05-03T13:00:32.000Z"
    },
    {
      "title": "How The CAVA (CAVA) Growth Story And Valuation Narrative Are Shifting After Recent Analyst Updates",
      "link": "https://finance.yahoo.com/markets/stocks/articles/cava-cava-growth-story-valuation-130835925.html",
      "publisher": "Simply Wall St.",
      "time": "2026-05-03T13:08:35.000Z"
    },
    {
      "title": "Broadcom’s New Wi-Fi 8 Push Adds Another Leg To Growth Story",
      "link": "https://finance.yahoo.com/markets/stocks/articles/broadcom-wi-fi-8-push-130842249.html",
      "publisher": "Simply Wall St.",
      "time": "2026-05-03T13:08:42.000Z"
    }
  ]
}