{
  "updated_at": "2026-05-20 09:00",
  "items": [
    {
      "title": "Take a closer look at Nvidia stock using Yahoo Finance's AlphaSpace",
      "link": "https://finance.yahoo.com/video/take-a-closer-look-at-nvidia-stock-using-yahoo-finances-alphaspace-140312172.html",
      "publisher": "Yahoo Finance Video",
      "time": "2026-05-19T14:03:12.000Z"
    },
    {
      "title": "Treasury yields climb as bond market weighs inflation concerns",
      "link": "https://finance.yahoo.com/video/treasury-yields-climb-as-bond-market-weighs-inflation-concerns-200826775.html",
      "publisher": "Yahoo Finance Video",
      "time": "2026-05-19T20:08:26.000Z"
    },
    {
      "title": "Take a look at Micron stock using Yahoo Finance's AlphaSpace",
      "link": "https://finance.yahoo.com/video/take-a-look-at-micron-stock-using-yahoo-finances-alphaspace-145841821.html",
      "publisher": "Yahoo Finance Video",
      "time": "2026-05-19T14:58:41.000Z"
    },
    {
      "title": "Israel finance minister says ICC seeks arrest warrant against him",
      "link": "https://finance.yahoo.com/m/652f59f6-715e-31cd-9939-2c3b8b067cf4/israel-finance-minister-says.html",
      "publisher": "AFP",
      "time": "2026-05-19T15:36:46.000Z"
    }
  ]
}